pyarimafft/__init__.py
pyarimafft-0.0.7.dist-info/METADATA
pyarimafft-0.0.7.dist-info/WHEEL
pyarimafft-0.0.7.dist-info/licenses/LICENSE
pyarimafft-0.0.7.dist-info/RECORD
