Metadata-Version: 2.4
Name: pyarimafft
Version: 0.0.7
Summary: Pyarimafft leverages LOESS regression for outlier cleaning, extracts key cyclicities via the fast fourier transform(fft) & performs time series forecasting with the cyclical features with ARIMA
Project-URL: Homepage, https://github.com/shashboy/pyarimafft
Project-URL: Issues, https://github.com/shashboy/pyarimafft
Author-email: Shashank Sharma <shashboy@gmail.com>
License-File: LICENSE
Classifier: License :: OSI Approved :: GNU General Public License v3 (GPLv3)
Classifier: Operating System :: OS Independent
Classifier: Programming Language :: Python :: 3
Requires-Python: >=3.8
